{
  "uid": "ilerna-redpanda",
  "title": "ILERNA Smart-Industry — Redpanda / Kafka",
  "tags": [
    "redpanda",
    "kafka",
    "pipeline"
  ],
  "timezone": "browser",
  "schemaVersion": 39,
  "version": 1,
  "refresh": "10s",
  "time": {
    "from": "now-30m",
    "to": "now"
  },
  "panels": [
    {
      "id": 1,
      "type": "stat",
      "title": "Brokers activos",
      "gridPos": {
        "x": 0,
        "y": 0,
        "w": 4,
        "h": 4
      },
      "datasource": {
        "type": "yesoreyeram-infinity-datasource",
        "uid": "infinity"
      },
      "options": {
        "colorMode": "background",
        "graphMode": "none",
        "reduceOptions": {
          "calcs": [
            "count"
          ]
        },
        "text": {}
      },
      "fieldConfig": {
        "defaults": {
          "color": {
            "mode": "fixed",
            "fixedColor": "green"
          },
          "unit": "short",
          "noValue": "0"
        }
      },
      "targets": [
        {
          "refId": "A",
          "type": "json",
          "source": "url",
          "format": "table",
          "url": "http://redpanda:9644/v1/brokers",
          "url_options": {
            "method": "GET"
          },
          "root_selector": "",
          "columns": [
            {
              "selector": "node_id",
              "text": "Node ID",
              "type": "number"
            },
            {
              "selector": "num_cores",
              "text": "Cores",
              "type": "number"
            },
            {
              "selector": "membership_status",
              "text": "Estado",
              "type": "string"
            }
          ],
          "parser": "backend"
        }
      ]
    },
    {
      "id": 2,
      "type": "stat",
      "title": "Topics del pipeline",
      "gridPos": {
        "x": 4,
        "y": 0,
        "w": 4,
        "h": 4
      },
      "datasource": {
        "type": "yesoreyeram-infinity-datasource",
        "uid": "infinity"
      },
      "options": {
        "colorMode": "background",
        "graphMode": "none",
        "reduceOptions": {
          "calcs": [
            "count"
          ]
        },
        "text": {}
      },
      "fieldConfig": {
        "defaults": {
          "color": {
            "mode": "fixed",
            "fixedColor": "blue"
          },
          "unit": "short",
          "noValue": "0"
        }
      },
      "targets": [
        {
          "refId": "A",
          "type": "json",
          "source": "inline",
          "format": "table",
          "data": "[{\"topic\":\"sensors_raw\"},{\"topic\":\"sensors_clean\"},{\"topic\":\"sensors_verified\"},{\"topic\":\"sensors_invalid\"}]",
          "columns": [
            {
              "selector": "topic",
              "text": "Topic",
              "type": "string"
            }
          ],
          "parser": "backend"
        }
      ]
    },
    {
      "id": 3,
      "type": "stat",
      "title": "Estado del cluster",
      "gridPos": {
        "x": 8,
        "y": 0,
        "w": 4,
        "h": 4
      },
      "datasource": {
        "type": "yesoreyeram-infinity-datasource",
        "uid": "infinity"
      },
      "options": {
        "colorMode": "background",
        "graphMode": "none",
        "reduceOptions": {
          "calcs": [
            "lastNotNull"
          ]
        },
        "text": {}
      },
      "fieldConfig": {
        "defaults": {
          "color": {
            "mode": "fixed",
            "fixedColor": "green"
          },
          "noValue": "—"
        }
      },
      "targets": [
        {
          "refId": "A",
          "type": "json",
          "source": "url",
          "format": "table",
          "url": "http://redpanda:9644/v1/cluster/health_overview",
          "url_options": {
            "method": "GET"
          },
          "root_selector": "",
          "columns": [
            {
              "selector": "is_healthy",
              "text": "Estado",
              "type": "string"
            }
          ],
          "parser": "backend"
        }
      ]
    },
    {
      "id": 4,
      "type": "table",
      "title": "Brokers — detalle",
      "gridPos": {
        "x": 0,
        "y": 4,
        "w": 12,
        "h": 6
      },
      "datasource": {
        "type": "yesoreyeram-infinity-datasource",
        "uid": "infinity"
      },
      "options": {
        "cellHeight": "sm",
        "footer": {
          "show": false
        }
      },
      "fieldConfig": {
        "defaults": {
          "custom": {
            "align": "left"
          }
        }
      },
      "targets": [
        {
          "refId": "A",
          "type": "json",
          "source": "url",
          "format": "table",
          "url": "http://redpanda:9644/v1/brokers",
          "url_options": {
            "method": "GET"
          },
          "root_selector": "",
          "columns": [
            {
              "selector": "node_id",
              "text": "Node ID",
              "type": "number"
            },
            {
              "selector": "num_cores",
              "text": "Cores",
              "type": "number"
            },
            {
              "selector": "membership_status",
              "text": "Membresía",
              "type": "string"
            },
            {
              "selector": "is_alive",
              "text": "Activo",
              "type": "boolean"
            },
            {
              "selector": "internal_rpc_address.address",
              "text": "Host",
              "type": "string"
            },
            {
              "selector": "internal_rpc_address.port",
              "text": "Puerto RPC",
              "type": "number"
            }
          ],
          "parser": "backend"
        }
      ]
    },
    {
      "id": 5,
      "type": "table",
      "title": "Topics — lista",
      "gridPos": {
        "x": 12,
        "y": 0,
        "w": 12,
        "h": 10
      },
      "datasource": {
        "type": "yesoreyeram-infinity-datasource",
        "uid": "infinity"
      },
      "options": {
        "cellHeight": "sm",
        "footer": {
          "show": false
        }
      },
      "fieldConfig": {
        "defaults": {
          "custom": {
            "align": "left"
          }
        },
        "overrides": [
          {
            "matcher": {
              "id": "byName",
              "options": "Topic"
            },
            "properties": [
              {
                "id": "custom.width",
                "value": 300
              },
              {
                "id": "custom.displayMode",
                "value": "color-background"
              },
              {
                "id": "color",
                "value": {
                  "mode": "fixed",
                  "fixedColor": "dark-blue"
                }
              }
            ]
          }
        ]
      },
      "targets": [
        {
          "refId": "A",
          "type": "json",
          "source": "inline",
          "format": "table",
          "data": "[{\"topic\":\"sensors_raw\",\"partition_count\":1,\"replication_factor\":1,\"is_internal\":false,\"compression\":\"none\"},{\"topic\":\"sensors_clean\",\"partition_count\":1,\"replication_factor\":1,\"is_internal\":false,\"compression\":\"none\"},{\"topic\":\"sensors_verified\",\"partition_count\":1,\"replication_factor\":1,\"is_internal\":false,\"compression\":\"none\"},{\"topic\":\"sensors_invalid\",\"partition_count\":1,\"replication_factor\":1,\"is_internal\":false,\"compression\":\"none\"}]",
          "columns": [
            {
              "selector": "topic",
              "text": "Topic",
              "type": "string"
            },
            {
              "selector": "partition_count",
              "text": "Particiones",
              "type": "number"
            },
            {
              "selector": "replication_factor",
              "text": "Réplicas",
              "type": "number"
            },
            {
              "selector": "is_internal",
              "text": "Interno",
              "type": "boolean"
            },
            {
              "selector": "compression",
              "text": "Compresión",
              "type": "string"
            }
          ],
          "parser": "backend"
        }
      ]
    },
    {
      "id": 6,
      "type": "stat",
      "title": "sensors_raw — mensajes",
      "description": "High-watermark: total mensajes escritos",
      "gridPos": { "x": 0, "y": 10, "w": 6, "h": 4 },
      "datasource": { "type": "yesoreyeram-infinity-datasource", "uid": "infinity" },
      "options": {
        "colorMode": "background",
        "graphMode": "none",
        "reduceOptions": { "calcs": ["lastNotNull"] },
        "text": {}
      },
      "fieldConfig": {
        "defaults": {
          "color": { "mode": "fixed", "fixedColor": "blue" },
          "unit": "short",
          "noValue": "0"
        }
      },
      "targets": [
        {
          "refId": "A",
          "type": "json",
          "source": "url",
          "format": "table",
          "parser": "backend",
          "url": "http://redpanda:9644/v1/partitions/kafka/sensors_raw/0",
          "url_options": { "method": "GET" },
          "root_selector": "",
          "columns": [{ "selector": "high_watermark", "text": "Mensajes", "type": "number" }]
        }
      ]
    },
    {
      "id": 7,
      "type": "stat",
      "title": "sensors_clean — mensajes",
      "description": "High-watermark: total mensajes escritos",
      "gridPos": { "x": 6, "y": 10, "w": 6, "h": 4 },
      "datasource": { "type": "yesoreyeram-infinity-datasource", "uid": "infinity" },
      "options": {
        "colorMode": "background",
        "graphMode": "none",
        "reduceOptions": { "calcs": ["lastNotNull"] },
        "text": {}
      },
      "fieldConfig": {
        "defaults": {
          "color": { "mode": "fixed", "fixedColor": "green" },
          "unit": "short",
          "noValue": "0"
        }
      },
      "targets": [
        {
          "refId": "A",
          "type": "json",
          "source": "url",
          "format": "table",
          "parser": "backend",
          "url": "http://redpanda:9644/v1/partitions/kafka/sensors_clean/0",
          "url_options": { "method": "GET" },
          "root_selector": "",
          "columns": [{ "selector": "high_watermark", "text": "Mensajes", "type": "number" }]
        }
      ]
    },
    {
      "id": 8,
      "type": "stat",
      "title": "sensors_verified — mensajes",
      "description": "High-watermark: total mensajes verificados (hash OK)",
      "gridPos": { "x": 12, "y": 10, "w": 6, "h": 4 },
      "datasource": { "type": "yesoreyeram-infinity-datasource", "uid": "infinity" },
      "options": {
        "colorMode": "background",
        "graphMode": "none",
        "reduceOptions": { "calcs": ["lastNotNull"] },
        "text": {}
      },
      "fieldConfig": {
        "defaults": {
          "color": { "mode": "fixed", "fixedColor": "green" },
          "unit": "short",
          "noValue": "0"
        }
      },
      "targets": [
        {
          "refId": "A",
          "type": "json",
          "source": "url",
          "format": "table",
          "parser": "backend",
          "url": "http://redpanda:9644/v1/partitions/kafka/sensors_verified/0",
          "url_options": { "method": "GET" },
          "root_selector": "",
          "columns": [{ "selector": "high_watermark", "text": "Mensajes", "type": "number" }]
        }
      ]
    },
    {
      "id": 9,
      "type": "stat",
      "title": "sensors_invalid (DLQ) — mensajes",
      "description": "High-watermark: mensajes rechazados por hash-chain",
      "gridPos": { "x": 18, "y": 10, "w": 6, "h": 4 },
      "datasource": { "type": "yesoreyeram-infinity-datasource", "uid": "infinity" },
      "options": {
        "colorMode": "background",
        "graphMode": "none",
        "reduceOptions": { "calcs": ["lastNotNull"] },
        "text": {}
      },
      "fieldConfig": {
        "defaults": {
          "color": { "mode": "fixed", "fixedColor": "orange" },
          "unit": "short",
          "noValue": "0"
        }
      },
      "targets": [
        {
          "refId": "A",
          "type": "json",
          "source": "url",
          "format": "table",
          "parser": "backend",
          "url": "http://redpanda:9644/v1/partitions/kafka/sensors_invalid/0",
          "url_options": { "method": "GET" },
          "root_selector": "",
          "columns": [{ "selector": "high_watermark", "text": "Mensajes", "type": "number" }]
        }
      ]
    }
  ]
}
